{
  "generated_at": "2026-01-08T09:36:26.078530+08:00",
  "total_titles_processed": 310,
  "failed_sources": [],
  "trends": [
    {
      "keyword_group": "ai 人工智能",
      "match_count": 6,
      "titles": [
        {
          "title": "直播电商新规强化AI内容监管",
          "url": "https://s.weibo.com/weibo?q=%23%E7%9B%B4%E6%92%AD%E7%94%B5%E5%95%86%E6%96%B0%E8%A7%84%E5%BC%BA%E5%8C%96AI%E5%86%85%E5%AE%B9%E7%9B%91%E7%AE%A1%23&t=31&band_rank=3&Refer=top",
          "source": "微博",
          "ranks": [
            3
          ],
          "is_new": false,
          "appearance_count": 1,
          "time_info": "09时36分"
        },
        {
          "title": "马斯克的2026愿景：我们已处于“技术奇点”，AI和机器人不可阻挡，短期是动荡和挑战，长期是丰盛时代",
          "url": "https://wallstreetcn.com/articles/3762706",
          "source": "华尔街见闻",
          "ranks": [
            5
          ],
          "is_new": false,
          "appearance_count": 1,
          "time_info": "09时36分"
        },
        {
          "title": "闪迪一夜暴涨28%！老黄一句话，存储行情又燃了，AI市场逻辑从“买铲子”转向“建仓库”",
          "url": "https://wallstreetcn.com/articles/3762702",
          "source": "华尔街见闻",
          "ranks": [
            6
          ],
          "is_new": false,
          "appearance_count": 1,
          "time_info": "09时36分"
        },
        {
          "title": "AI引爆存储芯片涨价潮！三星Q4营业利润飙升208% 创历史新高",
          "url": "https://www.cls.cn/detail/2251233",
          "source": "财联社热门",
          "ranks": [
            9
          ],
          "is_new": false,
          "appearance_count": 1,
          "time_info": "09时36分"
        },
        {
          "title": "合肥“十五五”规划建议：聚力打造全国领先的人工智能创新高地",
          "url": "https://wallstreetcn.com/livenews/3032819",
          "source": "华尔街见闻-快讯",
          "ranks": [
            9
          ],
          "is_new": false,
          "appearance_count": 1,
          "time_info": "09时36分"
        },
        {
          "title": "马斯克：中国AI算力领先世界",
          "url": "https://www.toutiao.com/trending/7592779381248888362/",
          "source": "今日头条",
          "ranks": [
            15
          ],
          "is_new": false,
          "appearance_count": 1,
          "time_info": "09时36分"
        }
      ]
    },
    {
      "keyword_group": "美股",
      "match_count": 2,
      "titles": [
        {
          "title": "美经济数据喜忧参半，美股涨势暂歇，美债受捧，美元两连涨，金银铜跌离高位",
          "url": "https://wallstreetcn.com/articles/3762734",
          "source": "华尔街见闻",
          "ranks": [
            2
          ],
          "is_new": false,
          "appearance_count": 1,
          "time_info": "09时36分"
        },
        {
          "title": "美股收盘：三大指数涨跌不一 国防股遭特朗普点名打压",
          "url": "https://www.cls.cn/detail/2251170",
          "source": "财联社热门",
          "ranks": [
            4
          ],
          "is_new": false,
          "appearance_count": 1,
          "time_info": "09时36分"
        }
      ]
    },
    {
      "keyword_group": "金价",
      "match_count": 1,
      "titles": [
        {
          "title": "金价已在历史高位 央行为何还在买",
          "url": "https://www.toutiao.com/trending/7592763349536869894/",
          "source": "今日头条",
          "ranks": [
            8
          ],
          "is_new": false,
          "appearance_count": 1,
          "time_info": "09时36分"
        }
      ]
    }
  ],
  "report_image_url": "https://joyce677.github.io/TrendRadar/img/news.jpg"
}